moodle/__init__.py
moodle/api.py
moodle/exceptions.py
moodle/moodle.py
moodle/py.typed
moods-0.1.19.dist-info/AUTHORS.md
moods-0.1.19.dist-info/LICENSE
moods-0.1.19.dist-info/METADATA
moods-0.1.19.dist-info/WHEEL
moods-0.1.19.dist-info/top_level.txt
moods-0.1.19.dist-info/RECORD
