Metadata-Version: 2.1
Name: moods
Version: 0.1.19
Summary: An API client for Moodle
Author-email: Jacob Sánchez <jacobszpz@protonmail.com>
Project-URL: Repository, https://github.com/sanjacob/moods
Project-URL: Bug Tracker, https://github.com/sanjacob/moods/issues
Classifier: Development Status :: 5 - Production/Stable
Classifier: Topic :: Internet :: WWW/HTTP
Classifier: Programming Language :: Python :: 3.10
Classifier: Programming Language :: Python :: 3.11
Classifier: Programming Language :: Python :: 3.12
Classifier: License :: OSI Approved :: GNU Lesser General Public License v2 (LGPLv2)
Classifier: Intended Audience :: Developers
Classifier: Operating System :: OS Independent
Classifier: Topic :: Software Development :: Libraries
Requires-Python: >=3.10
License-File: LICENSE
License-File: AUTHORS.md
Requires-Dist: requests
Requires-Dist: typing-extensions
Requires-Dist: tiny-api-client >=1.3.0
Requires-Dist: pydantic
Requires-Dist: pathvalidate
Requires-Dist: tzdata
Provides-Extra: docs
Requires-Dist: sphinx ; extra == 'docs'
Requires-Dist: sphinx-rtd-theme ; extra == 'docs'
Provides-Extra: test
Requires-Dist: pytest ; extra == 'test'
Requires-Dist: pytest-mock ; extra == 'test'
Requires-Dist: exceptiongroup ; extra == 'test'
Requires-Dist: mypy ; extra == 'test'
